Metadata-Version: 2.4
Name: koopa
Version: 0.0.14
Summary: Workflow for analysis of cellular microscopy data.
Home-page: https://github.com/bbquercus/koopa/
Author: Bastian Eichenberger
Author-email: bastian@eichenbergers.ch
License: MIT
Project-URL: Documentation, https://github.com/BBQuercus/koopa/wiki
Project-URL: Changelog, https://github.com/BBQuercus/koopa/releases
Project-URL: Issue Tracker, https://github.com/bbquercus/koopa/issues
Keywords: biomedical,bioinformatics,image analysis
Classifier: Development Status :: 3 - Alpha
Classifier: Environment :: Console
Classifier: Intended Audience :: Developers
Classifier: Intended Audience :: Science/Research
Classifier: License :: OSI Approved :: MIT License
Classifier: Operating System :: MacOS
Classifier: Operating System :: Microsoft :: Windows
Classifier: Operating System :: POSIX
Classifier: Operating System :: Unix
Classifier: Programming Language :: Python :: 3 :: Only
Classifier: Programming Language :: Python
Classifier: Topic :: Scientific/Engineering :: Bio-Informatics
Classifier: Topic :: Utilities
Requires-Python: >=3.7
Requires-Dist: czifile
Requires-Dist: numba
Requires-Dist: numpy
Requires-Dist: pandas
Requires-Dist: pyarrow
Requires-Dist: pystackreg
Requires-Dist: scikit-image
Requires-Dist: scipy
Requires-Dist: tifffile
Requires-Dist: trackpy
Provides-Extra: deepblink
Requires-Dist: tensorflow==2.7; extra == "deepblink"
Requires-Dist: deepblink; extra == "deepblink"
Provides-Extra: cellpose
Requires-Dist: torch==1.10.1; extra == "cellpose"
Requires-Dist: cellpose; extra == "cellpose"
Provides-Extra: segmodels
Requires-Dist: segmentation_models==1.0.1; extra == "segmodels"
Dynamic: author
Dynamic: author-email
Dynamic: classifier
Dynamic: description
Dynamic: description-content-type
Dynamic: home-page
Dynamic: keywords
Dynamic: license
Dynamic: project-url
Dynamic: provides-extra
Dynamic: requires-dist
Dynamic: requires-python
Dynamic: summary
